aiohttp_jwtplus/__init__.py
aiohttp_jwtplus/middleware.py
aiohttp_jwtplus/secrets.py
aiohttp_jwtplus/test_behav.py
aiohttp_jwtplus/utils.py
aiohttp_jwtplus-0.2.0.dist-info/LICENCE
aiohttp_jwtplus-0.2.0.dist-info/METADATA
aiohttp_jwtplus-0.2.0.dist-info/WHEEL
aiohttp_jwtplus-0.2.0.dist-info/top_level.txt
aiohttp_jwtplus-0.2.0.dist-info/RECORD
