Metadata-Version: 2.1
Name: aiohttp-jwtplus
Version: 0.2.0
Summary: Added a post router for improving security level of SPAs && auto refresh secrets. - GoodManWEN/aiohttp-jwtplus
Home-page: https://github.com/GoodManWEN/aiohttp-jwtplus
Author: WEN
License: UNKNOWN
Keywords: jwt,aiohttp,aiohttp-jwt,aiohttp-jwtplus
Platform: UNKNOWN
Classifier: Programming Language :: Python :: 3
Classifier: Programming Language :: Python :: 3.7
Classifier: Programming Language :: Python :: 3.8
Classifier: License :: OSI Approved :: MIT License
Classifier: Operating System :: POSIX :: Linux
Classifier: Operating System :: Microsoft :: Windows
Classifier: Framework :: AsyncIO
Requires-Python: >=3.7
Requires-Dist: aiohttp (>=2.3.5)
Requires-Dist: PyJWT (>=1.7.1)
